README.md
setup.py
instagramThiefBot/postToAccount.py
instagramThiefBot/thief.py
instagramthiefBot.egg-info/PKG-INFO
instagramthiefBot.egg-info/SOURCES.txt
instagramthiefBot.egg-info/dependency_links.txt
instagramthiefBot.egg-info/requires.txt
instagramthiefBot.egg-info/top_level.txt