Metadata-Version: 2.1
Name: instagramthiefBot
Version: 1.2
Summary: The Thief of Instagram
Home-page: UNKNOWN
Author: duckcouncil
Author-email: duckcouncil239@gmail.com
License: MIT
Platform: UNKNOWN
